<scene ambiant="0.5" AA="2" reflection_depth="2" filter=" "/>
<camera position="(15, 15, 0)" lookat="(0, 0, 0)" fov="90"/>
<light center="(0, 100, 0)" intensity="0.5" color="#FFFFFF"/>
<nottriangle center="(0, 0, 0)" side1="(20,  0,  0)" side2="(0, 10, 0)" normal="(0, 1, 0)" color="(50, 150, 50)" translation="(0, 0, 0)"/>
<plane center="(0, -1, 0)" normal="(0, 1, 0)" color="#D3D3D3"/>
<plane center="(0, 0, -40)" normal="(0, 0, 1)" color="#D3D3D3"/>
<triangle center="(8.507510, 0.043180, -9.711710)" side1="(8.423640, 0.137420, -9.578240)" side2="(8.349030, 0.076930, -9.625260)" normal="(0, 1, 0)" color="#FF00FF" refraction="1.1"/>
<triangle center="(7.245720, 1.677900, -9.812510)" side1="(6.576760, 1.218990, -8.880990)" side2="(7.277680, 1.778450, -8.581780)" normal="(0, 1, 0)" color="#FF00FF" refraction="1.1"/>
<triangle center="(7.307350, 1.439700, -8.267680)" side1="(6.576760, 1.218990, -8.880990)" side2="(6.487660, 0.775170, -8.784190)" normal="(0, 1, 0)" color="#FF00FF" refraction="1.1"/>
<triangle center="(8.507510, 0.043180, -9.711710)" side1="(8.349030, 0.076930, -9.625260)" side2="(8.324650, 0.051880, -9.726320)" normal="(0, 1, 0)" color="#FF00FF" refraction="1.1"/>
<triangle center="(7.245720, 1.677900, -9.812510)" side1="(6.267720, 0.928350, -9.725880)" side2="(6.576760, 1.218990, -8.880990)" normal="(0, 1, 0)" color="#FF00FF" refraction="1.1"/>
<triangle center="(6.487660, 0.775170, -8.784190)" side1="(6.267720, 0.928350, -9.725880)" side2="(6.219740, 0.499910, -9.894470)" normal="(0, 1, 0)" color="#FF00FF" refraction="1.1"/>
<triangle center="(8.507510, 0.043180, -9.711710)" side1="(8.324650, 0.051880, -9.726320)" side2="(8.364770, 0.076930, -9.822220)" normal="(0, 1, 0)" color="#FF00FF" refraction="1.1"/>
<triangle center="(7.245720, 1.677900, -9.812510)" side1="(6.531580, 1.076790, -10.621500)" side2="(6.267720, 0.928350, -9.725880)" normal="(0, 1, 0)" color="#FF00FF" refraction="1.1"/>
<triangle center="(6.219740, 0.499910, -9.894470)" side1="(6.531580, 1.076790, -10.621500)" side2="(6.660530, 0.775160, -10.948130)" normal="(0, 1, 0)" color="#FF00FF" refraction="1.1"/>
<triangle center="(8.507510, 0.043180, -9.711710)" side1="(8.364770, 0.076930, -9.822220)" side2="(8.445890, 0.137420, -9.856800)" normal="(0, 1, 0)" color="#FF00FF" refraction="1.1"/>
<triangle center="(7.245720, 1.677900, -9.812510)" side1="(7.213770, 1.577350, -11.043230)" side2="(6.531580, 1.076790, -10.621500)" normal="(0, 1, 0)" color="#FF00FF" refraction="1.1"/>
<triangle center="(6.660530, 0.775160, -10.948130)" side1="(7.213770, 1.577350, -11.043230)" side2="(7.551810, 1.439700, -11.327960)" normal="(0, 1, 0)" color="#FF00FF" refraction="1.1"/>
<triangle center="(8.507510, 0.043180, -9.711710)" side1="(8.445890, 0.137420, -9.856800)" side2="(8.520500, 0.197910, -9.809780)" normal="(0, 1, 0)" color="#FF00FF" refraction="1.1"/>
<triangle center="(7.245720, 1.677900, -9.812510)" side1="(7.914680, 2.136810, -10.744020)" side2="(7.213770, 1.577350, -11.043230)" normal="(0, 1, 0)" color="#FF00FF" refraction="1.1"/>
<triangle center="(7.551810, 1.439700, -11.327960)" side1="(7.914680, 2.136810, -10.744020)" side2="(8.371500, 2.104230, -10.811450)" normal="(0, 1, 0)" color="#FF00FF" refraction="1.1"/>
<triangle center="(8.507510, 0.043180, -9.711710)" side1="(8.520500, 0.197910, -9.809780)" side2="(8.544890, 0.222960, -9.708720)" normal="(0, 1, 0)" color="#FF00FF" refraction="1.1"/>
<triangle center="(7.245720, 1.677900, -9.812510)" side1="(8.223730, 2.427440, -9.899140)" side2="(7.914680, 2.136810, -10.744020)" normal="(0, 1, 0)" color="#FF00FF" refraction="1.1"/>
<triangle center="(8.371500, 2.104230, -10.811450)" side1="(8.223730, 2.427440, -9.899140)" side2="(8.639420, 2.379490, -9.701170)" normal="(0, 1, 0)" color="#FF00FF" refraction="1.1"/>
<triangle center="(8.507510, 0.043180, -9.711710)" side1="(8.544890, 0.222960, -9.708720)" side2="(8.504770, 0.197910, -9.612820)" normal="(0, 1, 0)" color="#FF00FF" refraction="1.1"/>
<triangle center="(7.245720, 1.677900, -9.812510)" side1="(7.959870, 2.279010, -9.003510)" side2="(8.223730, 2.427440, -9.899140)" normal="(0, 1, 0)" color="#FF00FF" refraction="1.1"/>
<triangle center="(8.639420, 2.379490, -9.701170)" side1="(7.959870, 2.279010, -9.003510)" side2="(8.198630, 2.104230, -8.647510)" normal="(0, 1, 0)" color="#FF00FF" refraction="1.1"/>
<triangle center="(8.507510, 0.043180, -9.711710)" side1="(8.504770, 0.197910, -9.612820)" side2="(8.423640, 0.137420, -9.578240)" normal="(0, 1, 0)" color="#FF00FF" refraction="1.1"/>
<triangle center="(7.245720, 1.677900, -9.812510)" side1="(7.277680, 1.778450, -8.581780)" side2="(7.959870, 2.279010, -9.003510)" normal="(0, 1, 0)" color="#FF00FF" refraction="1.1"/>
<triangle center="(8.198630, 2.104230, -8.647510)" side1="(7.277680, 1.778450, -8.581780)" side2="(7.307350, 1.439700, -8.267680)" normal="(0, 1, 0)" color="#FF00FF" refraction="1.1"/>
<triangle center="(8.131390, 1.468840, -8.100000)" side1="(7.558520, 1.097820, -8.087400)" side2="(8.423640, 0.137420, -9.578240)" normal="(0, 1, 0)" color="#FF00FF" refraction="1.1"/>
<triangle center="(7.307350, 1.439700, -8.267680)" side1="(7.502450, 1.170450, -8.091880)" side2="(8.007400, 1.629480, -8.109900)" normal="(0, 1, 0)" color="#FF00FF" refraction="1.1"/>
<triangle center="(8.963320, 2.055770, -8.995260)" side1="(8.542540, 1.831490, -8.506750)" side2="(8.504770, 0.197910, -9.612820)" normal="(0, 1, 0)" color="#FF00FF" refraction="1.1"/>
<triangle center="(8.198630, 2.104230, -8.647510)" side1="(8.486470, 1.904130, -8.511230)" side2="(8.839320, 2.216410, -9.005160)" normal="(0, 1, 0)" color="#FF00FF" refraction="1.1"/>
<triangle center="(9.071280, 2.055770, -10.346710)" side1="(9.029180, 2.135390, -9.670040)" side2="(8.544890, 0.222960, -9.708720)" normal="(0, 1, 0)" color="#FF00FF" refraction="1.1"/>
<triangle center="(8.639420, 2.379490, -9.701170)" side1="(8.973120, 2.208030, -9.674520)" side2="(8.947280, 2.216410, -10.356620)" normal="(0, 1, 0)" color="#FF00FF" refraction="1.1"/>
<triangle center="(8.392030, 1.468840, -11.362690)" side1="(8.733380, 1.831490, -10.895830)" side2="(8.520500, 0.197910, -9.809780)" normal="(0, 1, 0)" color="#FF00FF" refraction="1.1"/>
<triangle center="(8.371500, 2.104230, -10.811450)" side1="(8.677320, 1.904130, -10.900310)" side2="(8.268040, 1.629480, -11.372600)" normal="(0, 1, 0)" color="#FF00FF" refraction="1.1"/>
<triangle center="(7.323470, 0.638790, -11.448060)" side1="(7.828420, 1.097820, -11.466080)" side2="(8.445890, 0.137420, -9.856800)" normal="(0, 1, 0)" color="#FF00FF" refraction="1.1"/>
<triangle center="(7.551810, 1.439700, -11.327960)" side1="(7.772350, 1.170450, -11.470550)" side2="(7.199480, 0.799430, -11.457960)" normal="(0, 1, 0)" color="#FF00FF" refraction="1.1"/>
<triangle center="(6.491550, 0.051850, -10.552790)" side1="(6.844400, 0.364140, -11.046730)" side2="(8.364770, 0.076930, -9.822220)" normal="(0, 1, 0)" color="#FF00FF" refraction="1.1"/>
<triangle center="(6.660530, 0.775160, -10.948130)" side1="(6.788340, 0.436780, -11.051210)" side2="(6.367550, 0.212500, -10.562700)" normal="(0, 1, 0)" color="#FF00FF" refraction="1.1"/>
<triangle center="(6.383590, 0.051860, -9.201340)" side1="(6.357760, 0.060240, -9.883440)" side2="(8.324650, 0.051880, -9.726320)" normal="(0, 1, 0)" color="#FF00FF" refraction="1.1"/>
<triangle center="(6.219740, 0.499910, -9.894470)" side1="(6.301690, 0.132880, -9.887920)" side2="(6.259590, 0.212500, -9.211240)" normal="(0, 1, 0)" color="#FF00FF" refraction="1.1"/>
<triangle center="(7.062840, 0.638790, -8.185360)" side1="(6.653550, 0.364140, -8.657650)" side2="(8.349030, 0.076930, -9.625260)" normal="(0, 1, 0)" color="#FF00FF" refraction="1.1"/>
<triangle center="(6.487660, 0.775170, -8.784190)" side1="(6.597490, 0.436780, -8.662130)" side2="(6.938840, 0.799430, -8.195260)" normal="(0, 1, 0)" color="#FF00FF" refraction="1.1"/>
<triangle center="(8.423640, 0.137420, -9.578240)" side1="(8.504770, 0.197910, -9.612820)" side2="(8.131390, 1.468840, -8.100000)" normal="(0, 1, 0)" color="#FF00FF" refraction="1.1"/>
<triangle center="(8.504770, 0.197910, -9.612820)" side1="(8.542540, 1.831490, -8.506750)" side2="(8.131390, 1.468840, -8.100000)" normal="(0, 1, 0)" color="#FF00FF" refraction="1.1"/>
<triangle center="(8.007400, 1.629480, -8.109900)" side1="(8.486470, 1.904130, -8.511230)" side2="(8.198630, 2.104230, -8.647510)" normal="(0, 1, 0)" color="#FF00FF" refraction="1.1"/>
<triangle center="(8.198630, 2.104230, -8.647510)" side1="(7.307350, 1.439700, -8.267680)" side2="(8.007400, 1.629480, -8.109900)" normal="(0, 1, 0)" color="#FF00FF" refraction="1.1"/>
<triangle center="(8.504770, 0.197910, -9.612820)" side1="(8.544890, 0.222960, -9.708720)" side2="(8.963320, 2.055770, -8.995260)" normal="(0, 1, 0)" color="#FF00FF" refraction="1.1"/>
<triangle center="(8.544890, 0.222960, -9.708720)" side1="(9.029180, 2.135390, -9.670040)" side2="(8.963320, 2.055770, -8.995260)" normal="(0, 1, 0)" color="#FF00FF" refraction="1.1"/>
<triangle center="(8.839320, 2.216410, -9.005160)" side1="(8.973120, 2.208030, -9.674520)" side2="(8.639420, 2.379490, -9.701170)" normal="(0, 1, 0)" color="#FF00FF" refraction="1.1"/>
<triangle center="(8.639420, 2.379490, -9.701170)" side1="(8.198630, 2.104230, -8.647510)" side2="(8.839320, 2.216410, -9.005160)" normal="(0, 1, 0)" color="#FF00FF" refraction="1.1"/>
<triangle center="(8.544890, 0.222960, -9.708720)" side1="(8.520500, 0.197910, -9.809780)" side2="(9.071280, 2.055770, -10.346710)" normal="(0, 1, 0)" color="#FF00FF" refraction="1.1"/>
<triangle center="(8.520500, 0.197910, -9.809780)" side1="(8.733380, 1.831490, -10.895830)" side2="(9.071280, 2.055770, -10.346710)" normal="(0, 1, 0)" color="#FF00FF" refraction="1.1"/>
<triangle center="(8.947280, 2.216410, -10.356620)" side1="(8.677320, 1.904130, -10.900310)" side2="(8.371500, 2.104230, -10.811450)" normal="(0, 1, 0)" color="#FF00FF" refraction="1.1"/>
<triangle center="(8.371500, 2.104230, -10.811450)" side1="(8.639420, 2.379490, -9.701170)" side2="(8.947280, 2.216410, -10.356620)" normal="(0, 1, 0)" color="#FF00FF" refraction="1.1"/>
<triangle center="(8.520500, 0.197910, -9.809780)" side1="(8.445890, 0.137420, -9.856800)" side2="(8.392030, 1.468840, -11.362690)" normal="(0, 1, 0)" color="#FF00FF" refraction="1.1"/>
<triangle center="(8.445890, 0.137420, -9.856800)" side1="(7.828420, 1.097820, -11.466080)" side2="(8.392030, 1.468840, -11.362690)" normal="(0, 1, 0)" color="#FF00FF" refraction="1.1"/>
<triangle center="(8.268040, 1.629480, -11.372600)" side1="(7.772350, 1.170450, -11.470550)" side2="(7.551810, 1.439700, -11.327960)" normal="(0, 1, 0)" color="#FF00FF" refraction="1.1"/>
<triangle center="(7.551810, 1.439700, -11.327960)" side1="(8.371500, 2.104230, -10.811450)" side2="(8.268040, 1.629480, -11.372600)" normal="(0, 1, 0)" color="#FF00FF" refraction="1.1"/>
<triangle center="(8.445890, 0.137420, -9.856800)" side1="(8.364770, 0.076930, -9.822220)" side2="(7.323470, 0.638790, -11.448060)" normal="(0, 1, 0)" color="#FF00FF" refraction="1.1"/>
<triangle center="(8.364770, 0.076930, -9.822220)" side1="(6.844400, 0.364140, -11.046730)" side2="(7.323470, 0.638790, -11.448060)" normal="(0, 1, 0)" color="#FF00FF" refraction="1.1"/>
<triangle center="(7.199480, 0.799430, -11.457960)" side1="(6.788340, 0.436780, -11.051210)" side2="(6.660530, 0.775160, -10.948130)" normal="(0, 1, 0)" color="#FF00FF" refraction="1.1"/>
<triangle center="(6.660530, 0.775160, -10.948130)" side1="(7.551810, 1.439700, -11.327960)" side2="(7.199480, 0.799430, -11.457960)" normal="(0, 1, 0)" color="#FF00FF" refraction="1.1"/>
<triangle center="(8.364770, 0.076930, -9.822220)" side1="(8.324650, 0.051880, -9.726320)" side2="(6.491550, 0.051850, -10.552790)" normal="(0, 1, 0)" color="#FF00FF" refraction="1.1"/>
<triangle center="(8.324650, 0.051880, -9.726320)" side1="(6.357760, 0.060240, -9.883440)" side2="(6.491550, 0.051850, -10.552790)" normal="(0, 1, 0)" color="#FF00FF" refraction="1.1"/>
<triangle center="(6.367550, 0.212500, -10.562700)" side1="(6.301690, 0.132880, -9.887920)" side2="(6.219740, 0.499910, -9.894470)" normal="(0, 1, 0)" color="#FF00FF" refraction="1.1"/>
<triangle center="(6.219740, 0.499910, -9.894470)" side1="(6.660530, 0.775160, -10.948130)" side2="(6.367550, 0.212500, -10.562700)" normal="(0, 1, 0)" color="#FF00FF" refraction="1.1"/>
<triangle center="(8.324650, 0.051880, -9.726320)" side1="(8.349030, 0.076930, -9.625260)" side2="(6.383590, 0.051860, -9.201340)" normal="(0, 1, 0)" color="#FF00FF" refraction="1.1"/>
<triangle center="(8.349030, 0.076930, -9.625260)" side1="(6.653550, 0.364140, -8.657650)" side2="(6.383590, 0.051860, -9.201340)" normal="(0, 1, 0)" color="#FF00FF" refraction="1.1"/>
<triangle center="(6.259590, 0.212500, -9.211240)" side1="(6.597490, 0.436780, -8.662130)" side2="(6.487660, 0.775170, -8.784190)" normal="(0, 1, 0)" color="#FF00FF" refraction="1.1"/>
<triangle center="(6.487660, 0.775170, -8.784190)" side1="(6.219740, 0.499910, -9.894470)" side2="(6.259590, 0.212500, -9.211240)" normal="(0, 1, 0)" color="#FF00FF" refraction="1.1"/>
<triangle center="(8.349030, 0.076930, -9.625260)" side1="(8.423640, 0.137420, -9.578240)" side2="(7.062840, 0.638790, -8.185360)" normal="(0, 1, 0)" color="#FF00FF" refraction="1.1"/>
<triangle center="(8.423640, 0.137420, -9.578240)" side1="(7.558520, 1.097820, -8.087400)" side2="(7.062840, 0.638790, -8.185360)" normal="(0, 1, 0)" color="#FF00FF" refraction="1.1"/>
<triangle center="(6.938840, 0.799430, -8.195260)" side1="(7.502450, 1.170450, -8.091880)" side2="(7.307350, 1.439700, -8.267680)" normal="(0, 1, 0)" color="#FF00FF" refraction="1.1"/>
<triangle center="(7.307350, 1.439700, -8.267680)" side1="(6.487660, 0.775170, -8.784190)" side2="(6.938840, 0.799430, -8.195260)" normal="(0, 1, 0)" color="#FF00FF" refraction="1.1"/>
<triangle center="(7.307350, 1.439700, -8.267680)" side1="(7.277680, 1.778450, -8.581780)" side2="(6.576760, 1.218990, -8.880990)" normal="(0, 1, 0)" color="#FF00FF" refraction="1.1"/>
<triangle center="(6.487660, 0.775170, -8.784190)" side1="(6.576760, 1.218990, -8.880990)" side2="(6.267720, 0.928350, -9.725880)" normal="(0, 1, 0)" color="#FF00FF" refraction="1.1"/>
<triangle center="(6.219740, 0.499910, -9.894470)" side1="(6.267720, 0.928350, -9.725880)" side2="(6.531580, 1.076790, -10.621500)" normal="(0, 1, 0)" color="#FF00FF" refraction="1.1"/>
<triangle center="(6.660530, 0.775160, -10.948130)" side1="(6.531580, 1.076790, -10.621500)" side2="(7.213770, 1.577350, -11.043230)" normal="(0, 1, 0)" color="#FF00FF" refraction="1.1"/>
<triangle center="(7.551810, 1.439700, -11.327960)" side1="(7.213770, 1.577350, -11.043230)" side2="(7.914680, 2.136810, -10.744020)" normal="(0, 1, 0)" color="#FF00FF" refraction="1.1"/>
<triangle center="(8.371500, 2.104230, -10.811450)" side1="(7.914680, 2.136810, -10.744020)" side2="(8.223730, 2.427440, -9.899140)" normal="(0, 1, 0)" color="#FF00FF" refraction="1.1"/>
<triangle center="(8.639420, 2.379490, -9.701170)" side1="(8.223730, 2.427440, -9.899140)" side2="(7.959870, 2.279010, -9.003510)" normal="(0, 1, 0)" color="#FF00FF" refraction="1.1"/>
<triangle center="(8.198630, 2.104230, -8.647510)" side1="(7.959870, 2.279010, -9.003510)" side2="(7.277680, 1.778450, -8.581780)" normal="(0, 1, 0)" color="#FF00FF" refraction="1.1"/>
<triangle center="(4.824950, -0.012300, 4.747050)" side1="(4.950590, 0.084020, 4.646200)" side2="(5.006920, 0.022200, 4.716560)" normal="(0, 1, 0)" color="#FF00FF" refraction="1.1"/>
<triangle center="(6.009870, 1.658500, 5.266420)" side1="(6.967500, 1.189460, 4.590510)" side2="(6.390640, 1.761270, 4.067100)" normal="(0, 1, 0)" color="#FF00FF" refraction="1.1"/>
<triangle center="(6.467040, 1.415040, 3.753830)" side1="(6.967500, 1.189460, 4.590510)" side2="(7.085930, 0.735840, 4.526820)" normal="(0, 1, 0)" color="#FF00FF" refraction="1.1"/>
<triangle center="(4.824950, -0.012300, 4.747050)" side1="(5.006920, 0.022200, 4.716560)" side2="(4.996670, -0.003410, 4.822320)" normal="(0, 1, 0)" color="#FF00FF" refraction="1.1"/>
<triangle center="(6.009870, 1.658500, 5.266420)" side1="(6.983400, 0.892410, 5.509860)" side2="(6.967500, 1.189460, 4.590510)" normal="(0, 1, 0)" color="#FF00FF" refraction="1.1"/>
<triangle center="(7.085930, 0.735840, 4.526820)" side1="(6.983400, 0.892410, 5.509860)" side2="(6.973350, 0.454510, 5.688730)" normal="(0, 1, 0)" color="#FF00FF" refraction="1.1"/>
<triangle center="(4.824950, -0.012300, 4.747050)" side1="(4.996670, -0.003410, 4.822320)" side2="(4.925850, 0.022200, 4.901530)" normal="(0, 1, 0)" color="#FF00FF" refraction="1.1"/>
<triangle center="(6.009870, 1.658500, 5.266420)" side1="(6.429010, 1.044120, 6.286610)" side2="(6.983400, 0.892410, 5.509860)" normal="(0, 1, 0)" color="#FF00FF" refraction="1.1"/>
<triangle center="(6.973350, 0.454510, 5.688730)" side1="(6.429010, 1.044120, 6.286610)" side2="(6.195220, 0.735840, 6.558930)" normal="(0, 1, 0)" color="#FF00FF" refraction="1.1"/>
<triangle center="(4.824950, -0.012300, 4.747050)" side1="(4.925850, 0.022200, 4.901530)" side2="(4.835930, 0.084020, 4.907790)" normal="(0, 1, 0)" color="#FF00FF" refraction="1.1"/>
<triangle center="(6.009870, 1.658500, 5.266420)" side1="(5.629090, 1.555730, 6.465740)" side2="(6.429010, 1.044120, 6.286610)" normal="(0, 1, 0)" color="#FF00FF" refraction="1.1"/>
<triangle center="(6.195220, 0.735840, 6.558930)" side1="(5.629090, 1.555730, 6.465740)" side2="(5.207380, 1.415040, 6.627670)" normal="(0, 1, 0)" color="#FF00FF" refraction="1.1"/>
<triangle center="(4.824950, -0.012300, 4.747050)" side1="(4.835930, 0.084020, 4.907790)" side2="(4.779600, 0.145840, 4.837430)" normal="(0, 1, 0)" color="#FF00FF" refraction="1.1"/>
<triangle center="(6.009870, 1.658500, 5.266420)" side1="(5.052230, 2.127540, 5.942330)" side2="(5.629090, 1.555730, 6.465740)" normal="(0, 1, 0)" color="#FF00FF" refraction="1.1"/>
<triangle center="(5.207380, 1.415040, 6.627670)" side1="(5.052230, 2.127540, 5.942330)" side2="(4.588490, 2.094250, 5.854670)" normal="(0, 1, 0)" color="#FF00FF" refraction="1.1"/>
<triangle center="(4.824950, -0.012300, 4.747050)" side1="(4.779600, 0.145840, 4.837430)" side2="(4.789850, 0.171450, 4.731670)" normal="(0, 1, 0)" color="#FF00FF" refraction="1.1"/>
<triangle center="(6.009870, 1.658500, 5.266420)" side1="(5.036340, 2.424590, 5.022980)" side2="(5.052230, 2.127540, 5.942330)" normal="(0, 1, 0)" color="#FF00FF" refraction="1.1"/>
<triangle center="(4.588490, 2.094250, 5.854670)" side1="(5.036340, 2.424590, 5.022980)" side2="(4.701080, 2.375580, 4.692760)" normal="(0, 1, 0)" color="#FF00FF" refraction="1.1"/>
<triangle center="(4.824950, -0.012300, 4.747050)" side1="(4.789850, 0.171450, 4.731670)" side2="(4.860670, 0.145840, 4.652460)" normal="(0, 1, 0)" color="#FF00FF" refraction="1.1"/>
<triangle center="(6.009870, 1.658500, 5.266420)" side1="(5.590720, 2.272880, 4.246240)" side2="(5.036340, 2.424590, 5.022980)" normal="(0, 1, 0)" color="#FF00FF" refraction="1.1"/>
<triangle center="(4.701080, 2.375580, 4.692760)" side1="(5.590720, 2.272880, 4.246240)" side2="(5.479200, 2.094250, 3.822560)" normal="(0, 1, 0)" color="#FF00FF" refraction="1.1"/>
<triangle center="(4.824950, -0.012300, 4.747050)" side1="(4.860670, 0.145840, 4.652460)" side2="(4.950590, 0.084020, 4.646200)" normal="(0, 1, 0)" color="#FF00FF" refraction="1.1"/>
<triangle center="(6.009870, 1.658500, 5.266420)" side1="(6.390640, 1.761270, 4.067100)" side2="(5.590720, 2.272880, 4.246240)" normal="(0, 1, 0)" color="#FF00FF" refraction="1.1"/>
<triangle center="(5.479200, 2.094250, 3.822560)" side1="(6.390640, 1.761270, 4.067100)" side2="(6.467040, 1.415040, 3.753830)" normal="(0, 1, 0)" color="#FF00FF" refraction="1.1"/>
<triangle center="(5.727260, 1.444830, 3.316260)" side1="(6.284760, 1.065620, 3.495700)" side2="(4.950590, 0.084020, 4.646200)" normal="(0, 1, 0)" color="#FF00FF" refraction="1.1"/>
<triangle center="(6.467040, 1.415040, 3.753830)" side1="(6.337410, 1.139850, 3.518780)" side2="(5.843700, 1.609010, 3.367300)" normal="(0, 1, 0)" color="#FF00FF" refraction="1.1"/>
<triangle center="(4.624360, 2.044710, 3.902660)" side1="(5.194140, 1.815480, 3.571590)" side2="(4.860670, 0.145840, 4.652460)" normal="(0, 1, 0)" color="#FF00FF" refraction="1.1"/>
<triangle center="(5.479200, 2.094250, 3.822560)" side1="(5.246790, 1.889720, 3.594670)" side2="(4.740800, 2.208900, 3.953690)" normal="(0, 1, 0)" color="#FF00FF" refraction="1.1"/>
<triangle center="(4.068080, 2.044710, 5.171780)" side1="(4.335060, 2.126090, 4.532330)" side2="(4.789850, 0.171450, 4.731670)" normal="(0, 1, 0)" color="#FF00FF" refraction="1.1"/>
<triangle center="(4.701080, 2.375580, 4.692760)" side1="(4.387710, 2.200330, 4.555400)" side2="(4.184520, 2.208900, 5.222820)" normal="(0, 1, 0)" color="#FF00FF" refraction="1.1"/>
<triangle center="(4.384280, 1.444830, 6.380190)" side1="(4.210760, 1.815480, 5.815130)" side2="(4.779600, 0.145840, 4.837430)" normal="(0, 1, 0)" color="#FF00FF" refraction="1.1"/>
<triangle center="(4.588490, 2.094250, 5.854670)" side1="(4.263400, 1.889720, 5.838200)" side2="(4.500730, 1.609010, 6.431230)" normal="(0, 1, 0)" color="#FF00FF" refraction="1.1"/>
<triangle center="(5.387740, 0.596460, 6.820030)" side1="(4.894040, 1.065620, 6.668550)" side2="(4.835930, 0.084020, 4.907790)" normal="(0, 1, 0)" color="#FF00FF" refraction="1.1"/>
<triangle center="(5.207380, 1.415040, 6.627670)" side1="(4.946690, 1.139850, 6.691620)" side2="(5.504190, 0.760650, 6.871070)" normal="(0, 1, 0)" color="#FF00FF" refraction="1.1"/>
<triangle center="(6.490650, -0.003430, 6.233630)" side1="(5.984660, 0.315750, 6.592660)" side2="(4.925850, 0.022200, 4.901530)" normal="(0, 1, 0)" color="#FF00FF" refraction="1.1"/>
<triangle center="(6.195220, 0.735840, 6.558930)" side1="(6.037310, 0.389990, 6.615740)" side2="(6.607090, 0.160760, 6.284670)" normal="(0, 1, 0)" color="#FF00FF" refraction="1.1"/>
<triangle center="(7.046930, -0.003430, 4.964510)" side1="(6.843740, 0.005140, 5.631930)" side2="(4.996670, -0.003410, 4.822320)" normal="(0, 1, 0)" color="#FF00FF" refraction="1.1"/>
<triangle center="(6.973350, 0.454510, 5.688730)" side1="(6.896390, 0.079380, 5.655000)" side2="(7.163370, 0.160760, 5.015550)" normal="(0, 1, 0)" color="#FF00FF" refraction="1.1"/>
<triangle center="(6.730720, 0.596460, 3.756100)" side1="(6.968040, 0.315750, 4.349120)" side2="(5.006920, 0.022200, 4.716560)" normal="(0, 1, 0)" color="#FF00FF" refraction="1.1"/>
<triangle center="(7.085930, 0.735840, 4.526820)" side1="(7.020690, 0.389990, 4.372200)" side2="(6.847160, 0.760650, 3.807130)" normal="(0, 1, 0)" color="#FF00FF" refraction="1.1"/>
<triangle center="(4.950590, 0.084020, 4.646200)" side1="(4.860670, 0.145840, 4.652460)" side2="(5.727260, 1.444830, 3.316260)" normal="(0, 1, 0)" color="#FF00FF" refraction="1.1"/>
<triangle center="(4.860670, 0.145840, 4.652460)" side1="(5.194140, 1.815480, 3.571590)" side2="(5.727260, 1.444830, 3.316260)" normal="(0, 1, 0)" color="#FF00FF" refraction="1.1"/>
<triangle center="(5.843700, 1.609010, 3.367300)" side1="(5.246790, 1.889720, 3.594670)" side2="(5.479200, 2.094250, 3.822560)" normal="(0, 1, 0)" color="#FF00FF" refraction="1.1"/>
<triangle center="(5.479200, 2.094250, 3.822560)" side1="(6.467040, 1.415040, 3.753830)" side2="(5.843700, 1.609010, 3.367300)" normal="(0, 1, 0)" color="#FF00FF" refraction="1.1"/>
<triangle center="(4.860670, 0.145840, 4.652460)" side1="(4.789850, 0.171450, 4.731670)" side2="(4.624360, 2.044710, 3.902660)" normal="(0, 1, 0)" color="#FF00FF" refraction="1.1"/>
<triangle center="(4.789850, 0.171450, 4.731670)" side1="(4.335060, 2.126090, 4.532330)" side2="(4.624360, 2.044710, 3.902660)" normal="(0, 1, 0)" color="#FF00FF" refraction="1.1"/>
<triangle center="(4.740800, 2.208900, 3.953690)" side1="(4.387710, 2.200330, 4.555400)" side2="(4.701080, 2.375580, 4.692760)" normal="(0, 1, 0)" color="#FF00FF" refraction="1.1"/>
<triangle center="(4.701080, 2.375580, 4.692760)" side1="(5.479200, 2.094250, 3.822560)" side2="(4.740800, 2.208900, 3.953690)" normal="(0, 1, 0)" color="#FF00FF" refraction="1.1"/>
<triangle center="(4.789850, 0.171450, 4.731670)" side1="(4.779600, 0.145840, 4.837430)" side2="(4.068080, 2.044710, 5.171780)" normal="(0, 1, 0)" color="#FF00FF" refraction="1.1"/>
<triangle center="(4.779600, 0.145840, 4.837430)" side1="(4.210760, 1.815480, 5.815130)" side2="(4.068080, 2.044710, 5.171780)" normal="(0, 1, 0)" color="#FF00FF" refraction="1.1"/>
<triangle center="(4.184520, 2.208900, 5.222820)" side1="(4.263400, 1.889720, 5.838200)" side2="(4.588490, 2.094250, 5.854670)" normal="(0, 1, 0)" color="#FF00FF" refraction="1.1"/>
<triangle center="(4.588490, 2.094250, 5.854670)" side1="(4.701080, 2.375580, 4.692760)" side2="(4.184520, 2.208900, 5.222820)" normal="(0, 1, 0)" color="#FF00FF" refraction="1.1"/>
<triangle center="(4.779600, 0.145840, 4.837430)" side1="(4.835930, 0.084020, 4.907790)" side2="(4.384280, 1.444830, 6.380190)" normal="(0, 1, 0)" color="#FF00FF" refraction="1.1"/>
<triangle center="(4.835930, 0.084020, 4.907790)" side1="(4.894040, 1.065620, 6.668550)" side2="(4.384280, 1.444830, 6.380190)" normal="(0, 1, 0)" color="#FF00FF" refraction="1.1"/>
<triangle center="(4.500730, 1.609010, 6.431230)" side1="(4.946690, 1.139850, 6.691620)" side2="(5.207380, 1.415040, 6.627670)" normal="(0, 1, 0)" color="#FF00FF" refraction="1.1"/>
<triangle center="(5.207380, 1.415040, 6.627670)" side1="(4.588490, 2.094250, 5.854670)" side2="(4.500730, 1.609010, 6.431230)" normal="(0, 1, 0)" color="#FF00FF" refraction="1.1"/>
<triangle center="(4.835930, 0.084020, 4.907790)" side1="(4.925850, 0.022200, 4.901530)" side2="(5.387740, 0.596460, 6.820030)" normal="(0, 1, 0)" color="#FF00FF" refraction="1.1"/>
<triangle center="(4.925850, 0.022200, 4.901530)" side1="(5.984660, 0.315750, 6.592660)" side2="(5.387740, 0.596460, 6.820030)" normal="(0, 1, 0)" color="#FF00FF" refraction="1.1"/>
<triangle center="(5.504190, 0.760650, 6.871070)" side1="(6.037310, 0.389990, 6.615740)" side2="(6.195220, 0.735840, 6.558930)" normal="(0, 1, 0)" color="#FF00FF" refraction="1.1"/>
<triangle center="(6.195220, 0.735840, 6.558930)" side1="(5.207380, 1.415040, 6.627670)" side2="(5.504190, 0.760650, 6.871070)" normal="(0, 1, 0)" color="#FF00FF" refraction="1.1"/>
<triangle center="(4.925850, 0.022200, 4.901530)" side1="(4.996670, -0.003410, 4.822320)" side2="(6.490650, -0.003430, 6.233630)" normal="(0, 1, 0)" color="#FF00FF" refraction="1.1"/>
<triangle center="(4.996670, -0.003410, 4.822320)" side1="(6.843740, 0.005140, 5.631930)" side2="(6.490650, -0.003430, 6.233630)" normal="(0, 1, 0)" color="#FF00FF" refraction="1.1"/>
<triangle center="(6.607090, 0.160760, 6.284670)" side1="(6.896390, 0.079380, 5.655000)" side2="(6.973350, 0.454510, 5.688730)" normal="(0, 1, 0)" color="#FF00FF" refraction="1.1"/>
<triangle center="(6.973350, 0.454510, 5.688730)" side1="(6.195220, 0.735840, 6.558930)" side2="(6.607090, 0.160760, 6.284670)" normal="(0, 1, 0)" color="#FF00FF" refraction="1.1"/>
<triangle center="(4.996670, -0.003410, 4.822320)" side1="(5.006920, 0.022200, 4.716560)" side2="(7.046930, -0.003430, 4.964510)" normal="(0, 1, 0)" color="#FF00FF" refraction="1.1"/>
<triangle center="(5.006920, 0.022200, 4.716560)" side1="(6.968040, 0.315750, 4.349120)" side2="(7.046930, -0.003430, 4.964510)" normal="(0, 1, 0)" color="#FF00FF" refraction="1.1"/>
<triangle center="(7.163370, 0.160760, 5.015550)" side1="(7.020690, 0.389990, 4.372200)" side2="(7.085930, 0.735840, 4.526820)" normal="(0, 1, 0)" color="#FF00FF" refraction="1.1"/>
<triangle center="(7.085930, 0.735840, 4.526820)" side1="(6.973350, 0.454510, 5.688730)" side2="(7.163370, 0.160760, 5.015550)" normal="(0, 1, 0)" color="#FF00FF" refraction="1.1"/>
<triangle center="(5.006920, 0.022200, 4.716560)" side1="(4.950590, 0.084020, 4.646200)" side2="(6.730720, 0.596460, 3.756100)" normal="(0, 1, 0)" color="#FF00FF" refraction="1.1"/>
<triangle center="(4.950590, 0.084020, 4.646200)" side1="(6.284760, 1.065620, 3.495700)" side2="(6.730720, 0.596460, 3.756100)" normal="(0, 1, 0)" color="#FF00FF" refraction="1.1"/>
<triangle center="(6.847160, 0.760650, 3.807130)" side1="(6.337410, 1.139850, 3.518780)" side2="(6.467040, 1.415040, 3.753830)" normal="(0, 1, 0)" color="#FF00FF" refraction="1.1"/>
<triangle center="(6.467040, 1.415040, 3.753830)" side1="(7.085930, 0.735840, 4.526820)" side2="(6.847160, 0.760650, 3.807130)" normal="(0, 1, 0)" color="#FF00FF" refraction="1.1"/>
<triangle center="(6.467040, 1.415040, 3.753830)" side1="(6.390640, 1.761270, 4.067100)" side2="(6.967500, 1.189460, 4.590510)" normal="(0, 1, 0)" color="#FF00FF" refraction="1.1"/>
<triangle center="(7.085930, 0.735840, 4.526820)" side1="(6.967500, 1.189460, 4.590510)" side2="(6.983400, 0.892410, 5.509860)" normal="(0, 1, 0)" color="#FF00FF" refraction="1.1"/>
<triangle center="(6.973350, 0.454510, 5.688730)" side1="(6.983400, 0.892410, 5.509860)" side2="(6.429010, 1.044120, 6.286610)" normal="(0, 1, 0)" color="#FF00FF" refraction="1.1"/>
<triangle center="(6.195220, 0.735840, 6.558930)" side1="(6.429010, 1.044120, 6.286610)" side2="(5.629090, 1.555730, 6.465740)" normal="(0, 1, 0)" color="#FF00FF" refraction="1.1"/>
<triangle center="(5.207380, 1.415040, 6.627670)" side1="(5.629090, 1.555730, 6.465740)" side2="(5.052230, 2.127540, 5.942330)" normal="(0, 1, 0)" color="#FF00FF" refraction="1.1"/>
<triangle center="(4.588490, 2.094250, 5.854670)" side1="(5.052230, 2.127540, 5.942330)" side2="(5.036340, 2.424590, 5.022980)" normal="(0, 1, 0)" color="#FF00FF" refraction="1.1"/>
<triangle center="(4.701080, 2.375580, 4.692760)" side1="(5.036340, 2.424590, 5.022980)" side2="(5.590720, 2.272880, 4.246240)" normal="(0, 1, 0)" color="#FF00FF" refraction="1.1"/>
<triangle center="(5.479200, 2.094250, 3.822560)" side1="(5.590720, 2.272880, 4.246240)" side2="(6.390640, 1.761270, 4.067100)" normal="(0, 1, 0)" color="#FF00FF" refraction="1.1"/>
<triangle center="(9.857030, 0.022620, 1.016150)" side1="(10.034510, 0.155490, 1.149920)" side2="(9.959550, 0.070200, 1.249120)" normal="(0, 1, 0)" color="#FF00FF" refraction="1.1"/>
<triangle center="(9.564640, 2.327500, 2.776760)" side1="(10.793360, 1.680450, 3.827890)" side2="(11.297480, 2.469270, 2.878950)" normal="(0, 1, 0)" color="#FF00FF" refraction="1.1"/>
<triangle center="(11.742300, 1.991650, 2.874800)" side1="(10.793360, 1.680450, 3.827890)" side2="(10.918710, 1.054680, 3.964640)" normal="(0, 1, 0)" color="#FF00FF" refraction="1.1"/>
<triangle center="(9.857030, 0.022620, 1.016150)" side1="(9.959550, 0.070200, 1.249120)" side2="(9.814660, 0.034880, 1.271300)" normal="(0, 1, 0)" color="#FF00FF" refraction="1.1"/>
<triangle center="(9.564640, 2.327500, 2.776760)" side1="(9.569460, 1.270670, 4.161100)" side2="(10.793360, 1.680450, 3.827890)" normal="(0, 1, 0)" color="#FF00FF" refraction="1.1"/>
<triangle center="(10.918710, 1.054680, 3.964640)" side1="(9.569460, 1.270670, 4.161100)" side2="(9.326880, 0.666580, 4.208350)" normal="(0, 1, 0)" color="#FF00FF" refraction="1.1"/>
<triangle center="(9.857030, 0.022620, 1.016150)" side1="(9.814660, 0.034880, 1.271300)" side2="(9.684710, 0.070200, 1.203470)" normal="(0, 1, 0)" color="#FF00FF" refraction="1.1"/>
<triangle center="(9.564640, 2.327500, 2.776760)" side1="(8.342740, 1.479960, 3.683380)" side2="(9.569460, 1.270670, 4.161100)" normal="(0, 1, 0)" color="#FF00FF" refraction="1.1"/>
<triangle center="(9.326880, 0.666580, 4.208350)" side1="(8.342740, 1.479960, 3.683380)" side2="(7.899280, 1.054680, 3.463180)" normal="(0, 1, 0)" color="#FF00FF" refraction="1.1"/>
<triangle center="(9.857030, 0.022620, 1.016150)" side1="(9.684710, 0.070200, 1.203470)" side2="(9.645840, 0.155490, 1.085370)" normal="(0, 1, 0)" color="#FF00FF" refraction="1.1"/>
<triangle center="(9.564640, 2.327500, 2.776760)" side1="(7.831790, 2.185730, 2.674580)" side2="(8.342740, 1.479960, 3.683380)" normal="(0, 1, 0)" color="#FF00FF" refraction="1.1"/>
<triangle center="(7.899280, 1.054680, 3.463180)" side1="(7.831790, 2.185730, 2.674580)" side2="(7.472180, 1.991650, 2.165640)" normal="(0, 1, 0)" color="#FF00FF" refraction="1.1"/>
<triangle center="(9.857030, 0.022620, 1.016150)" side1="(9.645840, 0.155490, 1.085370)" side2="(9.720800, 0.240770, 0.986170)" normal="(0, 1, 0)" color="#FF00FF" refraction="1.1"/>
<triangle center="(9.564640, 2.327500, 2.776760)" side1="(8.335910, 2.974540, 1.725630)" side2="(7.831790, 2.185730, 2.674580)" normal="(0, 1, 0)" color="#FF00FF" refraction="1.1"/>
<triangle center="(7.472180, 1.991650, 2.165640)" side1="(8.335910, 2.974540, 1.725630)" side2="(8.295770, 2.928620, 1.075800)" normal="(0, 1, 0)" color="#FF00FF" refraction="1.1"/>
<triangle center="(9.857030, 0.022620, 1.016150)" side1="(9.720800, 0.240770, 0.986170)" side2="(9.865690, 0.276100, 0.963990)" normal="(0, 1, 0)" color="#FF00FF" refraction="1.1"/>
<triangle center="(9.564640, 2.327500, 2.776760)" side1="(9.559810, 3.384330, 1.392430)" side2="(8.335910, 2.974540, 1.725630)" normal="(0, 1, 0)" color="#FF00FF" refraction="1.1"/>
<triangle center="(8.295770, 2.928620, 1.075800)" side1="(9.559810, 3.384330, 1.392430)" side2="(9.887600, 3.316720, 0.832090)" normal="(0, 1, 0)" color="#FF00FF" refraction="1.1"/>
<triangle center="(9.857030, 0.022620, 1.016150)" side1="(9.865690, 0.276100, 0.963990)" side2="(9.995640, 0.240770, 1.031810)" normal="(0, 1, 0)" color="#FF00FF" refraction="1.1"/>
<triangle center="(9.564640, 2.327500, 2.776760)" side1="(10.786530, 3.175040, 1.870150)" side2="(9.559810, 3.384330, 1.392430)" normal="(0, 1, 0)" color="#FF00FF" refraction="1.1"/>
<triangle center="(9.887600, 3.316720, 0.832090)" side1="(10.786530, 3.175040, 1.870150)" side2="(11.315200, 2.928620, 1.577260)" normal="(0, 1, 0)" color="#FF00FF" refraction="1.1"/>
<triangle center="(9.857030, 0.022620, 1.016150)" side1="(9.995640, 0.240770, 1.031810)" side2="(10.034510, 0.155490, 1.149920)" normal="(0, 1, 0)" color="#FF00FF" refraction="1.1"/>
<triangle center="(9.564640, 2.327500, 2.776760)" side1="(11.297480, 2.469270, 2.878950)" side2="(10.786530, 3.175040, 1.870150)" normal="(0, 1, 0)" color="#FF00FF" refraction="1.1"/>
<triangle center="(11.315200, 2.928620, 1.577260)" side1="(11.297480, 2.469270, 2.878950)" side2="(11.742300, 1.991650, 2.874800)" normal="(0, 1, 0)" color="#FF00FF" refraction="1.1"/>
<triangle center="(12.076360, 2.032730, 1.737150)" side1="(12.025590, 1.509610, 2.543480)" side2="(10.034510, 0.155490, 1.149920)" normal="(0, 1, 0)" color="#FF00FF" refraction="1.1"/>
<triangle center="(11.742300, 1.991650, 2.874800)" side1="(12.012590, 1.612020, 2.621710)" side2="(12.047620, 2.259230, 1.910170)" normal="(0, 1, 0)" color="#FF00FF" refraction="1.1"/>
<triangle center="(10.918030, 2.860280, 0.461410)" side1="(11.554050, 2.544060, 1.110940)" side2="(9.995640, 0.240770, 1.031810)" normal="(0, 1, 0)" color="#FF00FF" refraction="1.1"/>
<triangle center="(11.315200, 2.928620, 1.577260)" side1="(11.541060, 2.646470, 1.189170)" side2="(10.889300, 3.086780, 0.634420)" normal="(0, 1, 0)" color="#FF00FF" refraction="1.1"/>
<triangle center="(9.032300, 2.860280, 0.148230)" side1="(9.977920, 2.972540, 0.288240)" side2="(9.865690, 0.276100, 0.963990)" normal="(0, 1, 0)" color="#FF00FF" refraction="1.1"/>
<triangle center="(9.887600, 3.316720, 0.832090)" side1="(9.964930, 3.074960, 0.366470)" side2="(9.003570, 3.086780, 0.321250)" normal="(0, 1, 0)" color="#FF00FF" refraction="1.1"/>
<triangle center="(7.523790, 2.032730, 0.981080)" side1="(8.220470, 2.544060, 0.557310)" side2="(9.720800, 0.240770, 0.986170)" normal="(0, 1, 0)" color="#FF00FF" refraction="1.1"/>
<triangle center="(8.295770, 2.928620, 1.075800)" side1="(8.207480, 2.646470, 0.635540)" side2="(7.495060, 2.259230, 1.154100)" normal="(0, 1, 0)" color="#FF00FF" refraction="1.1"/>
<triangle center="(7.276170, 0.862400, 2.472080)" side1="(7.311200, 1.509610, 1.760530)" side2="(9.645840, 0.155490, 1.085370)" normal="(0, 1, 0)" color="#FF00FF" refraction="1.1"/>
<triangle center="(7.472180, 1.991650, 2.165640)" side1="(7.298210, 1.612020, 1.838760)" side2="(7.247440, 1.088900, 2.645090)" normal="(0, 1, 0)" color="#FF00FF" refraction="1.1"/>
<triangle center="(8.434490, 0.034850, 3.747820)" side1="(7.782740, 0.475160, 3.193080)" side2="(9.684710, 0.070200, 1.203470)" normal="(0, 1, 0)" color="#FF00FF" refraction="1.1"/>
<triangle center="(7.899280, 1.054680, 3.463180)" side1="(7.769740, 0.577570, 3.271310)" side2="(8.405760, 0.261350, 3.920840)" normal="(0, 1, 0)" color="#FF00FF" refraction="1.1"/>
<triangle center="(10.320230, 0.034850, 4.061000)" side1="(9.358870, 0.046680, 4.015780)" side2="(9.814660, 0.034880, 1.271300)" normal="(0, 1, 0)" color="#FF00FF" refraction="1.1"/>
<triangle center="(9.326880, 0.666580, 4.208350)" side1="(9.345870, 0.149090, 4.094010)" side2="(10.291490, 0.261350, 4.234010)" normal="(0, 1, 0)" color="#FF00FF" refraction="1.1"/>
<triangle center="(11.828740, 0.862400, 3.228150)" side1="(11.116310, 0.475160, 3.746710)" side2="(9.959550, 0.070200, 1.249120)" normal="(0, 1, 0)" color="#FF00FF" refraction="1.1"/>
<triangle center="(10.918710, 1.054680, 3.964640)" side1="(11.103320, 0.577570, 3.824930)" side2="(11.800000, 1.088900, 3.401170)" normal="(0, 1, 0)" color="#FF00FF" refraction="1.1"/>
<triangle center="(10.034510, 0.155490, 1.149920)" side1="(9.995640, 0.240770, 1.031810)" side2="(12.076360, 2.032730, 1.737150)" normal="(0, 1, 0)" color="#FF00FF" refraction="1.1"/>
<triangle center="(9.995640, 0.240770, 1.031810)" side1="(11.554050, 2.544060, 1.110940)" side2="(12.076360, 2.032730, 1.737150)" normal="(0, 1, 0)" color="#FF00FF" refraction="1.1"/>
<triangle center="(12.047620, 2.259230, 1.910170)" side1="(11.541060, 2.646470, 1.189170)" side2="(11.315200, 2.928620, 1.577260)" normal="(0, 1, 0)" color="#FF00FF" refraction="1.1"/>
<triangle center="(11.315200, 2.928620, 1.577260)" side1="(11.742300, 1.991650, 2.874800)" side2="(12.047620, 2.259230, 1.910170)" normal="(0, 1, 0)" color="#FF00FF" refraction="1.1"/>
<triangle center="(9.995640, 0.240770, 1.031810)" side1="(9.865690, 0.276100, 0.963990)" side2="(10.918030, 2.860280, 0.461410)" normal="(0, 1, 0)" color="#FF00FF" refraction="1.1"/>
<triangle center="(9.865690, 0.276100, 0.963990)" side1="(9.977920, 2.972540, 0.288240)" side2="(10.918030, 2.860280, 0.461410)" normal="(0, 1, 0)" color="#FF00FF" refraction="1.1"/>
<triangle center="(10.889300, 3.086780, 0.634420)" side1="(9.964930, 3.074960, 0.366470)" side2="(9.887600, 3.316720, 0.832090)" normal="(0, 1, 0)" color="#FF00FF" refraction="1.1"/>
<triangle center="(9.887600, 3.316720, 0.832090)" side1="(11.315200, 2.928620, 1.577260)" side2="(10.889300, 3.086780, 0.634420)" normal="(0, 1, 0)" color="#FF00FF" refraction="1.1"/>
<triangle center="(9.865690, 0.276100, 0.963990)" side1="(9.720800, 0.240770, 0.986170)" side2="(9.032300, 2.860280, 0.148230)" normal="(0, 1, 0)" color="#FF00FF" refraction="1.1"/>
<triangle center="(9.720800, 0.240770, 0.986170)" side1="(8.220470, 2.544060, 0.557310)" side2="(9.032300, 2.860280, 0.148230)" normal="(0, 1, 0)" color="#FF00FF" refraction="1.1"/>
<triangle center="(9.003570, 3.086780, 0.321250)" side1="(8.207480, 2.646470, 0.635540)" side2="(8.295770, 2.928620, 1.075800)" normal="(0, 1, 0)" color="#FF00FF" refraction="1.1"/>
<triangle center="(8.295770, 2.928620, 1.075800)" side1="(9.887600, 3.316720, 0.832090)" side2="(9.003570, 3.086780, 0.321250)" normal="(0, 1, 0)" color="#FF00FF" refraction="1.1"/>
<triangle center="(9.720800, 0.240770, 0.986170)" side1="(9.645840, 0.155490, 1.085370)" side2="(7.523790, 2.032730, 0.981080)" normal="(0, 1, 0)" color="#FF00FF" refraction="1.1"/>
<triangle center="(9.645840, 0.155490, 1.085370)" side1="(7.311200, 1.509610, 1.760530)" side2="(7.523790, 2.032730, 0.981080)" normal="(0, 1, 0)" color="#FF00FF" refraction="1.1"/>
<triangle center="(7.495060, 2.259230, 1.154100)" side1="(7.298210, 1.612020, 1.838760)" side2="(7.472180, 1.991650, 2.165640)" normal="(0, 1, 0)" color="#FF00FF" refraction="1.1"/>
<triangle center="(7.472180, 1.991650, 2.165640)" side1="(8.295770, 2.928620, 1.075800)" side2="(7.495060, 2.259230, 1.154100)" normal="(0, 1, 0)" color="#FF00FF" refraction="1.1"/>
<triangle center="(9.645840, 0.155490, 1.085370)" side1="(9.684710, 0.070200, 1.203470)" side2="(7.276170, 0.862400, 2.472080)" normal="(0, 1, 0)" color="#FF00FF" refraction="1.1"/>
<triangle center="(9.684710, 0.070200, 1.203470)" side1="(7.782740, 0.475160, 3.193080)" side2="(7.276170, 0.862400, 2.472080)" normal="(0, 1, 0)" color="#FF00FF" refraction="1.1"/>
<triangle center="(7.247440, 1.088900, 2.645090)" side1="(7.769740, 0.577570, 3.271310)" side2="(7.899280, 1.054680, 3.463180)" normal="(0, 1, 0)" color="#FF00FF" refraction="1.1"/>
<triangle center="(7.899280, 1.054680, 3.463180)" side1="(7.472180, 1.991650, 2.165640)" side2="(7.247440, 1.088900, 2.645090)" normal="(0, 1, 0)" color="#FF00FF" refraction="1.1"/>
<triangle center="(9.684710, 0.070200, 1.203470)" side1="(9.814660, 0.034880, 1.271300)" side2="(8.434490, 0.034850, 3.747820)" normal="(0, 1, 0)" color="#FF00FF" refraction="1.1"/>
<triangle center="(9.814660, 0.034880, 1.271300)" side1="(9.358870, 0.046680, 4.015780)" side2="(8.434490, 0.034850, 3.747820)" normal="(0, 1, 0)" color="#FF00FF" refraction="1.1"/>
<triangle center="(8.405760, 0.261350, 3.920840)" side1="(9.345870, 0.149090, 4.094010)" side2="(9.326880, 0.666580, 4.208350)" normal="(0, 1, 0)" color="#FF00FF" refraction="1.1"/>
<triangle center="(9.326880, 0.666580, 4.208350)" side1="(7.899280, 1.054680, 3.463180)" side2="(8.405760, 0.261350, 3.920840)" normal="(0, 1, 0)" color="#FF00FF" refraction="1.1"/>
<triangle center="(9.814660, 0.034880, 1.271300)" side1="(9.959550, 0.070200, 1.249120)" side2="(10.320230, 0.034850, 4.061000)" normal="(0, 1, 0)" color="#FF00FF" refraction="1.1"/>
<triangle center="(9.959550, 0.070200, 1.249120)" side1="(11.116310, 0.475160, 3.746710)" side2="(10.320230, 0.034850, 4.061000)" normal="(0, 1, 0)" color="#FF00FF" refraction="1.1"/>
<triangle center="(10.291490, 0.261350, 4.234010)" side1="(11.103320, 0.577570, 3.824930)" side2="(10.918710, 1.054680, 3.964640)" normal="(0, 1, 0)" color="#FF00FF" refraction="1.1"/>
<triangle center="(10.918710, 1.054680, 3.964640)" side1="(9.326880, 0.666580, 4.208350)" side2="(10.291490, 0.261350, 4.234010)" normal="(0, 1, 0)" color="#FF00FF" refraction="1.1"/>
<triangle center="(9.959550, 0.070200, 1.249120)" side1="(10.034510, 0.155490, 1.149920)" side2="(11.828740, 0.862400, 3.228150)" normal="(0, 1, 0)" color="#FF00FF" refraction="1.1"/>
<triangle center="(10.034510, 0.155490, 1.149920)" side1="(12.025590, 1.509610, 2.543480)" side2="(11.828740, 0.862400, 3.228150)" normal="(0, 1, 0)" color="#FF00FF" refraction="1.1"/>
<triangle center="(11.800000, 1.088900, 3.401170)" side1="(12.012590, 1.612020, 2.621710)" side2="(11.742300, 1.991650, 2.874800)" normal="(0, 1, 0)" color="#FF00FF" refraction="1.1"/>
<triangle center="(11.742300, 1.991650, 2.874800)" side1="(10.918710, 1.054680, 3.964640)" side2="(11.800000, 1.088900, 3.401170)" normal="(0, 1, 0)" color="#FF00FF" refraction="1.1"/>
<triangle center="(11.742300, 1.991650, 2.874800)" side1="(11.297480, 2.469270, 2.878950)" side2="(10.793360, 1.680450, 3.827890)" normal="(0, 1, 0)" color="#FF00FF" refraction="1.1"/>
<triangle center="(10.918710, 1.054680, 3.964640)" side1="(10.793360, 1.680450, 3.827890)" side2="(9.569460, 1.270670, 4.161100)" normal="(0, 1, 0)" color="#FF00FF" refraction="1.1"/>
<triangle center="(9.326880, 0.666580, 4.208350)" side1="(9.569460, 1.270670, 4.161100)" side2="(8.342740, 1.479960, 3.683380)" normal="(0, 1, 0)" color="#FF00FF" refraction="1.1"/>
<triangle center="(7.899280, 1.054680, 3.463180)" side1="(8.342740, 1.479960, 3.683380)" side2="(7.831790, 2.185730, 2.674580)" normal="(0, 1, 0)" color="#FF00FF" refraction="1.1"/>
<triangle center="(7.472180, 1.991650, 2.165640)" side1="(7.831790, 2.185730, 2.674580)" side2="(8.335910, 2.974540, 1.725630)" normal="(0, 1, 0)" color="#FF00FF" refraction="1.1"/>
<triangle center="(8.295770, 2.928620, 1.075800)" side1="(8.335910, 2.974540, 1.725630)" side2="(9.559810, 3.384330, 1.392430)" normal="(0, 1, 0)" color="#FF00FF" refraction="1.1"/>
<triangle center="(9.887600, 3.316720, 0.832090)" side1="(9.559810, 3.384330, 1.392430)" side2="(10.786530, 3.175040, 1.870150)" normal="(0, 1, 0)" color="#FF00FF" refraction="1.1"/>
<triangle center="(11.315200, 2.928620, 1.577260)" side1="(10.786530, 3.175040, 1.870150)" side2="(11.297480, 2.469270, 2.878950)" normal="(0, 1, 0)" color="#FF00FF" refraction="1.1"/>
<triangle center="(10.266360, 0.019720, -2.415200)" side1="(10.080920, 0.274980, -2.799790)" side2="(10.296210, 0.111140, -2.903260)" normal="(0, 1, 0)" color="#FF00FF" refraction="1.1"/>
<triangle center="(12.314510, 4.447650, -5.164890)" side1="(11.140660, 3.204610, -8.040980)" side2="(9.444910, 4.720010, -6.863770)" normal="(0, 1, 0)" color="#FF00FF" refraction="1.1"/>
<triangle center="(8.681580, 3.802450, -7.247980)" side1="(11.140660, 3.204610, -8.040980)" side2="(11.046870, 2.002440, -8.384790)" normal="(0, 1, 0)" color="#FF00FF" refraction="1.1"/>
<triangle center="(10.266360, 0.019720, -2.415200)" side1="(10.296210, 0.111140, -2.903260)" side2="(10.563180, 0.043270, -2.813690)" normal="(0, 1, 0)" color="#FF00FF" refraction="1.1"/>
<triangle center="(12.314510, 4.447650, -5.164890)" side1="(13.524030, 2.417360, -7.533410)" side2="(11.140660, 3.204610, -8.040980)" normal="(0, 1, 0)" color="#FF00FF" refraction="1.1"/>
<triangle center="(11.046870, 2.002440, -8.384790)" side1="(13.524030, 2.417360, -7.533410)" side2="(13.979900, 1.256840, -7.400730)" normal="(0, 1, 0)" color="#FF00FF" refraction="1.1"/>
<triangle center="(10.266360, 0.019720, -2.415200)" side1="(10.563180, 0.043270, -2.813690)" side2="(10.725440, 0.111140, -2.583540)" normal="(0, 1, 0)" color="#FF00FF" refraction="1.1"/>
<triangle center="(12.314510, 4.447650, -5.164890)" side1="(15.198880, 2.819430, -5.638410)" side2="(13.524030, 2.417360, -7.533410)" normal="(0, 1, 0)" color="#FF00FF" refraction="1.1"/>
<triangle center="(13.979900, 1.256840, -7.400730)" side1="(15.198880, 2.819430, -5.638410)" side2="(15.762550, 2.002430, -4.872240)" normal="(0, 1, 0)" color="#FF00FF" refraction="1.1"/>
<triangle center="(10.266360, 0.019720, -2.415200)" side1="(10.725440, 0.111140, -2.583540)" side2="(10.687940, 0.274980, -2.347640)" normal="(0, 1, 0)" color="#FF00FF" refraction="1.1"/>
<triangle center="(12.314510, 4.447650, -5.164890)" side1="(15.184110, 4.175290, -3.466020)" side2="(15.198880, 2.819430, -5.638410)" normal="(0, 1, 0)" color="#FF00FF" refraction="1.1"/>
<triangle center="(15.762550, 2.002430, -4.872240)" side1="(15.184110, 4.175290, -3.466020)" side2="(15.350560, 3.802450, -2.280480)" normal="(0, 1, 0)" color="#FF00FF" refraction="1.1"/>
<triangle center="(10.266360, 0.019720, -2.415200)" side1="(10.687940, 0.274980, -2.347640)" side2="(10.472650, 0.438820, -2.244160)" normal="(0, 1, 0)" color="#FF00FF" refraction="1.1"/>
<triangle center="(12.314510, 4.447650, -5.164890)" side1="(13.488360, 5.690700, -2.288810)" side2="(15.184110, 4.175290, -3.466020)" normal="(0, 1, 0)" color="#FF00FF" refraction="1.1"/>
<triangle center="(15.350560, 3.802450, -2.280480)" side1="(13.488360, 5.690700, -2.288810)" side2="(12.985270, 5.602470, -1.143670)" normal="(0, 1, 0)" color="#FF00FF" refraction="1.1"/>
<triangle center="(10.266360, 0.019720, -2.415200)" side1="(10.472650, 0.438820, -2.244160)" side2="(10.205680, 0.506690, -2.333730)" normal="(0, 1, 0)" color="#FF00FF" refraction="1.1"/>
<triangle center="(12.314510, 4.447650, -5.164890)" side1="(11.104990, 6.477950, -2.796370)" side2="(13.488360, 5.690700, -2.288810)" normal="(0, 1, 0)" color="#FF00FF" refraction="1.1"/>
<triangle center="(12.985270, 5.602470, -1.143670)" side1="(11.104990, 6.477950, -2.796370)" side2="(10.052240, 6.348060, -2.127740)" normal="(0, 1, 0)" color="#FF00FF" refraction="1.1"/>
<triangle center="(10.266360, 0.019720, -2.415200)" side1="(10.205680, 0.506690, -2.333730)" side2="(10.043410, 0.438820, -2.563880)" normal="(0, 1, 0)" color="#FF00FF" refraction="1.1"/>
<triangle center="(12.314510, 4.447650, -5.164890)" side1="(9.430140, 6.075870, -4.691380)" side2="(11.104990, 6.477950, -2.796370)" normal="(0, 1, 0)" color="#FF00FF" refraction="1.1"/>
<triangle center="(10.052240, 6.348060, -2.127740)" side1="(9.430140, 6.075870, -4.691380)" side2="(8.269590, 5.602470, -4.656220)" normal="(0, 1, 0)" color="#FF00FF" refraction="1.1"/>
<triangle center="(10.266360, 0.019720, -2.415200)" side1="(10.043410, 0.438820, -2.563880)" side2="(10.080920, 0.274980, -2.799790)" normal="(0, 1, 0)" color="#FF00FF" refraction="1.1"/>
<triangle center="(12.314510, 4.447650, -5.164890)" side1="(9.444910, 4.720010, -6.863770)" side2="(9.430140, 6.075870, -4.691380)" normal="(0, 1, 0)" color="#FF00FF" refraction="1.1"/>
<triangle center="(8.269590, 5.602470, -4.656220)" side1="(9.444910, 4.720010, -6.863770)" side2="(8.681580, 3.802450, -7.247980)" normal="(0, 1, 0)" color="#FF00FF" refraction="1.1"/>
<triangle center="(7.110280, 3.881380, -5.598880)" side1="(7.906300, 2.876400, -6.931330)" side2="(10.080920, 0.274980, -2.799790)" normal="(0, 1, 0)" color="#FF00FF" refraction="1.1"/>
<triangle center="(8.681580, 3.802450, -7.247980)" side1="(7.997300, 3.073150, -7.053510)" side2="(7.311550, 4.316510, -5.869090)" normal="(0, 1, 0)" color="#FF00FF" refraction="1.1"/>
<triangle center="(7.966300, 5.471200, -2.401110)" side1="(7.451440, 4.863690, -4.069920)" side2="(10.043410, 0.438820, -2.563880)" normal="(0, 1, 0)" color="#FF00FF" refraction="1.1"/>
<triangle center="(8.269590, 5.602470, -4.656220)" side1="(7.542450, 5.060440, -4.192100)" side2="(8.167580, 5.906330, -2.671320)" normal="(0, 1, 0)" color="#FF00FF" refraction="1.1"/>
<triangle center="(10.911410, 5.471200, -0.207400)" side1="(9.419570, 5.686860, -1.278360)" side2="(10.205680, 0.506690, -2.333730)" normal="(0, 1, 0)" color="#FF00FF" refraction="1.1"/>
<triangle center="(10.052240, 6.348060, -2.127740)" side1="(9.510570, 5.883610, -1.400540)" side2="(11.112680, 5.906330, -0.477620)" normal="(0, 1, 0)" color="#FF00FF" refraction="1.1"/>
<triangle center="(14.220390, 3.881380, -0.302800)" side1="(12.657760, 4.863690, -0.191910)" side2="(10.472650, 0.438820, -2.244160)" normal="(0, 1, 0)" color="#FF00FF" refraction="1.1"/>
<triangle center="(12.985270, 5.602470, -1.143670)" side1="(12.748770, 5.060440, -0.314090)" side2="(14.421670, 4.316510, -0.573010)" normal="(0, 1, 0)" color="#FF00FF" refraction="1.1"/>
<triangle center="(15.954900, 1.633030, -2.631410)" side1="(15.269140, 2.876400, -1.447000)" side2="(10.687940, 0.274980, -2.347640)" normal="(0, 1, 0)" color="#FF00FF" refraction="1.1"/>
<triangle center="(15.350560, 3.802450, -2.280480)" side1="(15.360150, 3.073150, -1.569180)" side2="(16.156170, 2.068170, -2.901630)" normal="(0, 1, 0)" color="#FF00FF" refraction="1.1"/>
<triangle center="(15.098870, 0.043210, -5.829180)" side1="(15.724000, 0.889100, -4.308410)" side2="(10.725440, 0.111140, -2.583540)" normal="(0, 1, 0)" color="#FF00FF" refraction="1.1"/>
<triangle center="(15.762550, 2.002430, -4.872240)" side1="(15.815000, 1.085850, -4.430580)" side2="(15.300150, 0.478350, -6.099390)" normal="(0, 1, 0)" color="#FF00FF" refraction="1.1"/>
<triangle center="(12.153770, 0.043210, -8.022890)" side1="(13.755880, 0.065940, -7.099960)" side2="(10.563180, 0.043270, -2.813690)" normal="(0, 1, 0)" color="#FF00FF" refraction="1.1"/>
<triangle center="(13.979900, 1.256840, -7.400730)" side1="(13.846880, 0.262690, -7.222140)" side2="(12.355040, 0.478350, -8.293100)" normal="(0, 1, 0)" color="#FF00FF" refraction="1.1"/>
<triangle center="(8.844780, 1.633030, -7.927490)" side1="(10.517680, 0.889100, -8.186410)" side2="(10.296210, 0.111140, -2.903260)" normal="(0, 1, 0)" color="#FF00FF" refraction="1.1"/>
<triangle center="(11.046870, 2.002440, -8.384790)" side1="(10.608690, 1.085850, -8.308590)" side2="(9.046060, 2.068170, -8.197710)" normal="(0, 1, 0)" color="#FF00FF" refraction="1.1"/>
<triangle center="(10.080920, 0.274980, -2.799790)" side1="(10.043410, 0.438820, -2.563880)" side2="(7.110280, 3.881380, -5.598880)" normal="(0, 1, 0)" color="#FF00FF" refraction="1.1"/>
<triangle center="(10.043410, 0.438820, -2.563880)" side1="(7.451440, 4.863690, -4.069920)" side2="(7.110280, 3.881380, -5.598880)" normal="(0, 1, 0)" color="#FF00FF" refraction="1.1"/>
<triangle center="(7.311550, 4.316510, -5.869090)" side1="(7.542450, 5.060440, -4.192100)" side2="(8.269590, 5.602470, -4.656220)" normal="(0, 1, 0)" color="#FF00FF" refraction="1.1"/>
<triangle center="(8.269590, 5.602470, -4.656220)" side1="(8.681580, 3.802450, -7.247980)" side2="(7.311550, 4.316510, -5.869090)" normal="(0, 1, 0)" color="#FF00FF" refraction="1.1"/>
<triangle center="(10.043410, 0.438820, -2.563880)" side1="(10.205680, 0.506690, -2.333730)" side2="(7.966300, 5.471200, -2.401110)" normal="(0, 1, 0)" color="#FF00FF" refraction="1.1"/>
<triangle center="(10.205680, 0.506690, -2.333730)" side1="(9.419570, 5.686860, -1.278360)" side2="(7.966300, 5.471200, -2.401110)" normal="(0, 1, 0)" color="#FF00FF" refraction="1.1"/>
<triangle center="(8.167580, 5.906330, -2.671320)" side1="(9.510570, 5.883610, -1.400540)" side2="(10.052240, 6.348060, -2.127740)" normal="(0, 1, 0)" color="#FF00FF" refraction="1.1"/>
<triangle center="(10.052240, 6.348060, -2.127740)" side1="(8.269590, 5.602470, -4.656220)" side2="(8.167580, 5.906330, -2.671320)" normal="(0, 1, 0)" color="#FF00FF" refraction="1.1"/>
<triangle center="(10.205680, 0.506690, -2.333730)" side1="(10.472650, 0.438820, -2.244160)" side2="(10.911410, 5.471200, -0.207400)" normal="(0, 1, 0)" color="#FF00FF" refraction="1.1"/>
<triangle center="(10.472650, 0.438820, -2.244160)" side1="(12.657760, 4.863690, -0.191910)" side2="(10.911410, 5.471200, -0.207400)" normal="(0, 1, 0)" color="#FF00FF" refraction="1.1"/>
<triangle center="(11.112680, 5.906330, -0.477620)" side1="(12.748770, 5.060440, -0.314090)" side2="(12.985270, 5.602470, -1.143670)" normal="(0, 1, 0)" color="#FF00FF" refraction="1.1"/>
<triangle center="(12.985270, 5.602470, -1.143670)" side1="(10.052240, 6.348060, -2.127740)" side2="(11.112680, 5.906330, -0.477620)" normal="(0, 1, 0)" color="#FF00FF" refraction="1.1"/>
<triangle center="(10.472650, 0.438820, -2.244160)" side1="(10.687940, 0.274980, -2.347640)" side2="(14.220390, 3.881380, -0.302800)" normal="(0, 1, 0)" color="#FF00FF" refraction="1.1"/>
<triangle center="(10.687940, 0.274980, -2.347640)" side1="(15.269140, 2.876400, -1.447000)" side2="(14.220390, 3.881380, -0.302800)" normal="(0, 1, 0)" color="#FF00FF" refraction="1.1"/>
<triangle center="(14.421670, 4.316510, -0.573010)" side1="(15.360150, 3.073150, -1.569180)" side2="(15.350560, 3.802450, -2.280480)" normal="(0, 1, 0)" color="#FF00FF" refraction="1.1"/>
<triangle center="(15.350560, 3.802450, -2.280480)" side1="(12.985270, 5.602470, -1.143670)" side2="(14.421670, 4.316510, -0.573010)" normal="(0, 1, 0)" color="#FF00FF" refraction="1.1"/>
<triangle center="(10.687940, 0.274980, -2.347640)" side1="(10.725440, 0.111140, -2.583540)" side2="(15.954900, 1.633030, -2.631410)" normal="(0, 1, 0)" color="#FF00FF" refraction="1.1"/>
<triangle center="(10.725440, 0.111140, -2.583540)" side1="(15.724000, 0.889100, -4.308410)" side2="(15.954900, 1.633030, -2.631410)" normal="(0, 1, 0)" color="#FF00FF" refraction="1.1"/>
<triangle center="(16.156170, 2.068170, -2.901630)" side1="(15.815000, 1.085850, -4.430580)" side2="(15.762550, 2.002430, -4.872240)" normal="(0, 1, 0)" color="#FF00FF" refraction="1.1"/>
<triangle center="(15.762550, 2.002430, -4.872240)" side1="(15.350560, 3.802450, -2.280480)" side2="(16.156170, 2.068170, -2.901630)" normal="(0, 1, 0)" color="#FF00FF" refraction="1.1"/>
<triangle center="(10.725440, 0.111140, -2.583540)" side1="(10.563180, 0.043270, -2.813690)" side2="(15.098870, 0.043210, -5.829180)" normal="(0, 1, 0)" color="#FF00FF" refraction="1.1"/>
<triangle center="(10.563180, 0.043270, -2.813690)" side1="(13.755880, 0.065940, -7.099960)" side2="(15.098870, 0.043210, -5.829180)" normal="(0, 1, 0)" color="#FF00FF" refraction="1.1"/>
<triangle center="(15.300150, 0.478350, -6.099390)" side1="(13.846880, 0.262690, -7.222140)" side2="(13.979900, 1.256840, -7.400730)" normal="(0, 1, 0)" color="#FF00FF" refraction="1.1"/>
<triangle center="(13.979900, 1.256840, -7.400730)" side1="(15.762550, 2.002430, -4.872240)" side2="(15.300150, 0.478350, -6.099390)" normal="(0, 1, 0)" color="#FF00FF" refraction="1.1"/>
<triangle center="(10.563180, 0.043270, -2.813690)" side1="(10.296210, 0.111140, -2.903260)" side2="(12.153770, 0.043210, -8.022890)" normal="(0, 1, 0)" color="#FF00FF" refraction="1.1"/>
<triangle center="(10.296210, 0.111140, -2.903260)" side1="(10.517680, 0.889100, -8.186410)" side2="(12.153770, 0.043210, -8.022890)" normal="(0, 1, 0)" color="#FF00FF" refraction="1.1"/>
<triangle center="(12.355040, 0.478350, -8.293100)" side1="(10.608690, 1.085850, -8.308590)" side2="(11.046870, 2.002440, -8.384790)" normal="(0, 1, 0)" color="#FF00FF" refraction="1.1"/>
<triangle center="(11.046870, 2.002440, -8.384790)" side1="(13.979900, 1.256840, -7.400730)" side2="(12.355040, 0.478350, -8.293100)" normal="(0, 1, 0)" color="#FF00FF" refraction="1.1"/>
<triangle center="(10.296210, 0.111140, -2.903260)" side1="(10.080920, 0.274980, -2.799790)" side2="(8.844780, 1.633030, -7.927490)" normal="(0, 1, 0)" color="#FF00FF" refraction="1.1"/>
<triangle center="(10.080920, 0.274980, -2.799790)" side1="(7.906300, 2.876400, -6.931330)" side2="(8.844780, 1.633030, -7.927490)" normal="(0, 1, 0)" color="#FF00FF" refraction="1.1"/>
<triangle center="(9.046060, 2.068170, -8.197710)" side1="(7.997300, 3.073150, -7.053510)" side2="(8.681580, 3.802450, -7.247980)" normal="(0, 1, 0)" color="#FF00FF" refraction="1.1"/>
<triangle center="(8.681580, 3.802450, -7.247980)" side1="(11.046870, 2.002440, -8.384790)" side2="(9.046060, 2.068170, -8.197710)" normal="(0, 1, 0)" color="#FF00FF" refraction="1.1"/>
<triangle center="(8.681580, 3.802450, -7.247980)" side1="(9.444910, 4.720010, -6.863770)" side2="(11.140660, 3.204610, -8.040980)" normal="(0, 1, 0)" color="#FF00FF" refraction="1.1"/>
<triangle center="(11.046870, 2.002440, -8.384790)" side1="(11.140660, 3.204610, -8.040980)" side2="(13.524030, 2.417360, -7.533410)" normal="(0, 1, 0)" color="#FF00FF" refraction="1.1"/>
<triangle center="(13.979900, 1.256840, -7.400730)" side1="(13.524030, 2.417360, -7.533410)" side2="(15.198880, 2.819430, -5.638410)" normal="(0, 1, 0)" color="#FF00FF" refraction="1.1"/>
<triangle center="(15.762550, 2.002430, -4.872240)" side1="(15.198880, 2.819430, -5.638410)" side2="(15.184110, 4.175290, -3.466020)" normal="(0, 1, 0)" color="#FF00FF" refraction="1.1"/>
<triangle center="(15.350560, 3.802450, -2.280480)" side1="(15.184110, 4.175290, -3.466020)" side2="(13.488360, 5.690700, -2.288810)" normal="(0, 1, 0)" color="#FF00FF" refraction="1.1"/>
<triangle center="(12.985270, 5.602470, -1.143670)" side1="(13.488360, 5.690700, -2.288810)" side2="(11.104990, 6.477950, -2.796370)" normal="(0, 1, 0)" color="#FF00FF" refraction="1.1"/>
<triangle center="(10.052240, 6.348060, -2.127740)" side1="(11.104990, 6.477950, -2.796370)" side2="(9.430140, 6.075870, -4.691380)" normal="(0, 1, 0)" color="#FF00FF" refraction="1.1"/>
<triangle center="(8.269590, 5.602470, -4.656220)" side1="(9.430140, 6.075870, -4.691380)" side2="(9.444910, 4.720010, -6.863770)" normal="(0, 1, 0)" color="#FF00FF" refraction="1.1"/>
<triangle center="(3.252200, -0.016750, 1.078610)" side1="(2.427180, 0.517780, 1.423150)" side2="(2.235010, 0.174690, 0.961350)" normal="(0, 1, 0)" color="#FF00FF" refraction="1.1"/>
<triangle center="(-2.267280, 9.255460, -3.513070)" side1="(-8.413100, 6.652490, -1.381730)" side2="(-6.142090, 9.825790, 2.296370)" normal="(0, 1, 0)" color="#FF00FF" refraction="1.1"/>
<triangle center="(-7.031260, 7.904390, 3.849340)" side1="(-8.413100, 6.652490, -1.381730)" side2="(-9.142550, 4.135110, -1.224240)" normal="(0, 1, 0)" color="#FF00FF" refraction="1.1"/>
<triangle center="(3.252200, -0.016750, 1.078610)" side1="(2.235010, 0.174690, 0.961350)" side2="(2.452300, 0.032580, 0.413170)" normal="(0, 1, 0)" color="#FF00FF" refraction="1.1"/>
<triangle center="(-2.267280, 9.255460, -3.513070)" side1="(-7.083970, 5.003970, -6.308350)" side2="(-8.413100, 6.652490, -1.381730)" normal="(0, 1, 0)" color="#FF00FF" refraction="1.1"/>
<triangle center="(-9.142550, 4.135110, -1.224240)" side1="(-7.083970, 5.003970, -6.308350)" side2="(-6.755280, 2.573820, -7.246660)" normal="(0, 1, 0)" color="#FF00FF" refraction="1.1"/>
<triangle center="(3.252200, -0.016750, 1.078610)" side1="(2.452300, 0.032580, 0.413170)" side2="(2.951780, 0.174690, 0.099750)" normal="(0, 1, 0)" color="#FF00FF" refraction="1.1"/>
<triangle center="(-2.267280, 9.255460, -3.513070)" side1="(-2.933290, 5.845920, -9.597530)" side2="(-7.083970, 5.003970, -6.308350)" normal="(0, 1, 0)" color="#FF00FF" refraction="1.1"/>
<triangle center="(-6.755280, 2.573820, -7.246660)" side1="(-2.933290, 5.845920, -9.597530)" side2="(-1.267880, 4.135110, -10.690070)" normal="(0, 1, 0)" color="#FF00FF" refraction="1.1"/>
<triangle center="(3.252200, -0.016750, 1.078610)" side1="(2.951780, 0.174690, 0.099750)" side2="(3.440850, 0.517780, 0.204670)" normal="(0, 1, 0)" color="#FF00FF" refraction="1.1"/>
<triangle center="(-2.267280, 9.255460, -3.513070)" side1="(1.607530, 8.685130, -9.322520)" side2="(-2.933290, 5.845920, -9.597530)" normal="(0, 1, 0)" color="#FF00FF" refraction="1.1"/>
<triangle center="(-1.267880, 4.135110, -10.690070)" side1="(1.607530, 8.685130, -9.322520)" side2="(4.105210, 7.904390, -9.537370)" normal="(0, 1, 0)" color="#FF00FF" refraction="1.1"/>
<triangle center="(3.252200, -0.016750, 1.078610)" side1="(3.440850, 0.517780, 0.204670)" side2="(3.633020, 0.860860, 0.666480)" normal="(0, 1, 0)" color="#FF00FF" refraction="1.1"/>
<triangle center="(-2.267280, 9.255460, -3.513070)" side1="(3.878530, 11.858430, -5.644420)" side2="(1.607530, 8.685130, -9.322520)" normal="(0, 1, 0)" color="#FF00FF" refraction="1.1"/>
<triangle center="(4.105210, 7.904390, -9.537370)" side1="(3.878530, 11.858430, -5.644420)" side2="(6.216500, 11.673670, -4.463780)" normal="(0, 1, 0)" color="#FF00FF" refraction="1.1"/>
<triangle center="(3.252200, -0.016750, 1.078610)" side1="(3.633020, 0.860860, 0.666480)" side2="(3.415730, 1.002970, 1.214650)" normal="(0, 1, 0)" color="#FF00FF" refraction="1.1"/>
<triangle center="(-2.267280, 9.255460, -3.513070)" side1="(2.549400, 13.506940, -0.717800)" side2="(3.878530, 11.858430, -5.644420)" normal="(0, 1, 0)" color="#FF00FF" refraction="1.1"/>
<triangle center="(6.216500, 11.673670, -4.463780)" side1="(2.549400, 13.506940, -0.717800)" side2="(3.829230, 13.234960, 1.558640)" normal="(0, 1, 0)" color="#FF00FF" refraction="1.1"/>
<triangle center="(3.252200, -0.016750, 1.078610)" side1="(3.415730, 1.002970, 1.214650)" side2="(2.916250, 0.860860, 1.528080)" normal="(0, 1, 0)" color="#FF00FF" refraction="1.1"/>
<triangle center="(-2.267280, 9.255460, -3.513070)" side1="(-1.601280, 12.664990, 2.571380)" side2="(2.549400, 13.506940, -0.717800)" normal="(0, 1, 0)" color="#FF00FF" refraction="1.1"/>
<triangle center="(3.829230, 13.234960, 1.558640)" side1="(-1.601280, 12.664990, 2.571380)" side2="(-1.658180, 11.673670, 5.002050)" normal="(0, 1, 0)" color="#FF00FF" refraction="1.1"/>
<triangle center="(3.252200, -0.016750, 1.078610)" side1="(2.916250, 0.860860, 1.528080)" side2="(2.427180, 0.517780, 1.423150)" normal="(0, 1, 0)" color="#FF00FF" refraction="1.1"/>
<triangle center="(-2.267280, 9.255460, -3.513070)" side1="(-6.142090, 9.825790, 2.296370)" side2="(-1.601280, 12.664990, 2.571380)" normal="(0, 1, 0)" color="#FF00FF" refraction="1.1"/>
<triangle center="(-1.658180, 11.673670, 5.002050)" side1="(-6.142090, 9.825790, 2.296370)" side2="(-7.031260, 7.904390, 3.849340)" normal="(0, 1, 0)" color="#FF00FF" refraction="1.1"/>
<triangle center="(-3.759540, 8.069660, 7.320250)" side1="(-6.456260, 5.965210, 5.506040)" side2="(2.427180, 0.517780, 1.423150)" normal="(0, 1, 0)" color="#FF00FF" refraction="1.1"/>
<triangle center="(-7.031260, 7.904390, 3.849340)" side1="(-6.701510, 6.377210, 5.302010)" side2="(-4.301940, 8.980840, 6.869020)" normal="(0, 1, 0)" color="#FF00FF" refraction="1.1"/>
<triangle center="(3.023200, 11.398780, 5.889620)" side1="(-0.524140, 10.126660, 6.778670)" side2="(2.916250, 0.860860, 1.528080)" normal="(0, 1, 0)" color="#FF00FF" refraction="1.1"/>
<triangle center="(-1.658180, 11.673670, 5.002050)" side1="(-0.769390, 10.538650, 6.574650)" side2="(2.480800, 12.309960, 5.438400)" normal="(0, 1, 0)" color="#FF00FF" refraction="1.1"/>
<triangle center="(7.941200, 11.398780, -0.022110)" side1="(5.534180, 11.850380, 2.977000)" side2="(3.415730, 1.002970, 1.214650)" normal="(0, 1, 0)" color="#FF00FF" refraction="1.1"/>
<triangle center="(3.829230, 13.234960, 1.558640)" side1="(5.288930, 12.262380, 2.772980)" side2="(7.398800, 12.309960, -0.473340)" normal="(0, 1, 0)" color="#FF00FF" refraction="1.1"/>
<triangle center="(8.113560, 8.069660, -6.951940)" side1="(8.169830, 10.126660, -3.672010)" side2="(3.633020, 0.860860, 0.666480)" normal="(0, 1, 0)" color="#FF00FF" refraction="1.1"/>
<triangle center="(6.216500, 11.673670, -4.463780)" side1="(7.924580, 10.538650, -3.876030)" side2="(7.571160, 8.980840, -7.403170)" normal="(0, 1, 0)" color="#FF00FF" refraction="1.1"/>
<triangle center="(3.439310, 3.361570, -10.840470)" side1="(5.838880, 5.965210, -9.273460)" side2="(3.440850, 0.517780, 0.204670)" normal="(0, 1, 0)" color="#FF00FF" refraction="1.1"/>
<triangle center="(4.105210, 7.904390, -9.537370)" side1="(5.593630, 6.377210, -9.477480)" side2="(2.896910, 4.272760, -11.291690)" normal="(0, 1, 0)" color="#FF00FF" refraction="1.1"/>
<triangle center="(-3.343430, 0.032450, -9.409850)" side1="(-0.093240, 1.803770, -10.546100)" side2="(2.951780, 0.174690, 0.099750)" normal="(0, 1, 0)" color="#FF00FF" refraction="1.1"/>
<triangle center="(-1.267880, 4.135110, -10.690070)" side1="(-0.338490, 2.215760, -10.750120)" side2="(-3.885830, 0.943640, -9.861070)" normal="(0, 1, 0)" color="#FF00FF" refraction="1.1"/>
<triangle center="(-8.261430, 0.032450, -3.498110)" side1="(-6.151560, 0.080040, -6.744430)" side2="(2.452300, 0.032580, 0.413170)" normal="(0, 1, 0)" color="#FF00FF" refraction="1.1"/>
<triangle center="(-6.755280, 2.573820, -7.246660)" side1="(-6.396810, 0.492030, -6.948450)" side2="(-8.803830, 0.943640, -3.949340)" normal="(0, 1, 0)" color="#FF00FF" refraction="1.1"/>
<triangle center="(-8.433790, 3.361580, 3.431720)" side1="(-8.787210, 1.803770, -0.095410)" side2="(2.235010, 0.174690, 0.961350)" normal="(0, 1, 0)" color="#FF00FF" refraction="1.1"/>
<triangle center="(-9.142550, 4.135110, -1.224240)" side1="(-9.032460, 2.215760, -0.299440)" side2="(-8.976190, 4.272760, 2.980490)" normal="(0, 1, 0)" color="#FF00FF" refraction="1.1"/>
<triangle center="(2.427180, 0.517780, 1.423150)" side1="(2.916250, 0.860860, 1.528080)" side2="(-3.759540, 8.069660, 7.320250)" normal="(0, 1, 0)" color="#FF00FF" refraction="1.1"/>
<triangle center="(2.916250, 0.860860, 1.528080)" side1="(-0.524140, 10.126660, 6.778670)" side2="(-3.759540, 8.069660, 7.320250)" normal="(0, 1, 0)" color="#FF00FF" refraction="1.1"/>
<triangle center="(-4.301940, 8.980840, 6.869020)" side1="(-0.769390, 10.538650, 6.574650)" side2="(-1.658180, 11.673670, 5.002050)" normal="(0, 1, 0)" color="#FF00FF" refraction="1.1"/>
<triangle center="(-1.658180, 11.673670, 5.002050)" side1="(-7.031260, 7.904390, 3.849340)" side2="(-4.301940, 8.980840, 6.869020)" normal="(0, 1, 0)" color="#FF00FF" refraction="1.1"/>
<triangle center="(2.916250, 0.860860, 1.528080)" side1="(3.415730, 1.002970, 1.214650)" side2="(3.023200, 11.398780, 5.889620)" normal="(0, 1, 0)" color="#FF00FF" refraction="1.1"/>
<triangle center="(3.415730, 1.002970, 1.214650)" side1="(5.534180, 11.850380, 2.977000)" side2="(3.023200, 11.398780, 5.889620)" normal="(0, 1, 0)" color="#FF00FF" refraction="1.1"/>
<triangle center="(2.480800, 12.309960, 5.438400)" side1="(5.288930, 12.262380, 2.772980)" side2="(3.829230, 13.234960, 1.558640)" normal="(0, 1, 0)" color="#FF00FF" refraction="1.1"/>
<triangle center="(3.829230, 13.234960, 1.558640)" side1="(-1.658180, 11.673670, 5.002050)" side2="(2.480800, 12.309960, 5.438400)" normal="(0, 1, 0)" color="#FF00FF" refraction="1.1"/>
<triangle center="(3.415730, 1.002970, 1.214650)" side1="(3.633020, 0.860860, 0.666480)" side2="(7.941200, 11.398780, -0.022110)" normal="(0, 1, 0)" color="#FF00FF" refraction="1.1"/>
<triangle center="(3.633020, 0.860860, 0.666480)" side1="(8.169830, 10.126660, -3.672010)" side2="(7.941200, 11.398780, -0.022110)" normal="(0, 1, 0)" color="#FF00FF" refraction="1.1"/>
<triangle center="(7.398800, 12.309960, -0.473340)" side1="(7.924580, 10.538650, -3.876030)" side2="(6.216500, 11.673670, -4.463780)" normal="(0, 1, 0)" color="#FF00FF" refraction="1.1"/>
<triangle center="(6.216500, 11.673670, -4.463780)" side1="(3.829230, 13.234960, 1.558640)" side2="(7.398800, 12.309960, -0.473340)" normal="(0, 1, 0)" color="#FF00FF" refraction="1.1"/>
<triangle center="(3.633020, 0.860860, 0.666480)" side1="(3.440850, 0.517780, 0.204670)" side2="(8.113560, 8.069660, -6.951940)" normal="(0, 1, 0)" color="#FF00FF" refraction="1.1"/>
<triangle center="(3.440850, 0.517780, 0.204670)" side1="(5.838880, 5.965210, -9.273460)" side2="(8.113560, 8.069660, -6.951940)" normal="(0, 1, 0)" color="#FF00FF" refraction="1.1"/>
<triangle center="(7.571160, 8.980840, -7.403170)" side1="(5.593630, 6.377210, -9.477480)" side2="(4.105210, 7.904390, -9.537370)" normal="(0, 1, 0)" color="#FF00FF" refraction="1.1"/>
<triangle center="(4.105210, 7.904390, -9.537370)" side1="(6.216500, 11.673670, -4.463780)" side2="(7.571160, 8.980840, -7.403170)" normal="(0, 1, 0)" color="#FF00FF" refraction="1.1"/>
<triangle center="(3.440850, 0.517780, 0.204670)" side1="(2.951780, 0.174690, 0.099750)" side2="(3.439310, 3.361570, -10.840470)" normal="(0, 1, 0)" color="#FF00FF" refraction="1.1"/>
<triangle center="(2.951780, 0.174690, 0.099750)" side1="(-0.093240, 1.803770, -10.546100)" side2="(3.439310, 3.361570, -10.840470)" normal="(0, 1, 0)" color="#FF00FF" refraction="1.1"/>
<triangle center="(2.896910, 4.272760, -11.291690)" side1="(-0.338490, 2.215760, -10.750120)" side2="(-1.267880, 4.135110, -10.690070)" normal="(0, 1, 0)" color="#FF00FF" refraction="1.1"/>
<triangle center="(-1.267880, 4.135110, -10.690070)" side1="(4.105210, 7.904390, -9.537370)" side2="(2.896910, 4.272760, -11.291690)" normal="(0, 1, 0)" color="#FF00FF" refraction="1.1"/>
<triangle center="(2.951780, 0.174690, 0.099750)" side1="(2.452300, 0.032580, 0.413170)" side2="(-3.343430, 0.032450, -9.409850)" normal="(0, 1, 0)" color="#FF00FF" refraction="1.1"/>
<triangle center="(2.452300, 0.032580, 0.413170)" side1="(-6.151560, 0.080040, -6.744430)" side2="(-3.343430, 0.032450, -9.409850)" normal="(0, 1, 0)" color="#FF00FF" refraction="1.1"/>
<triangle center="(-3.885830, 0.943640, -9.861070)" side1="(-6.396810, 0.492030, -6.948450)" side2="(-6.755280, 2.573820, -7.246660)" normal="(0, 1, 0)" color="#FF00FF" refraction="1.1"/>
<triangle center="(-6.755280, 2.573820, -7.246660)" side1="(-1.267880, 4.135110, -10.690070)" side2="(-3.885830, 0.943640, -9.861070)" normal="(0, 1, 0)" color="#FF00FF" refraction="1.1"/>
<triangle center="(2.452300, 0.032580, 0.413170)" side1="(2.235010, 0.174690, 0.961350)" side2="(-8.261430, 0.032450, -3.498110)" normal="(0, 1, 0)" color="#FF00FF" refraction="1.1"/>
<triangle center="(2.235010, 0.174690, 0.961350)" side1="(-8.787210, 1.803770, -0.095410)" side2="(-8.261430, 0.032450, -3.498110)" normal="(0, 1, 0)" color="#FF00FF" refraction="1.1"/>
<triangle center="(-8.803830, 0.943640, -3.949340)" side1="(-9.032460, 2.215760, -0.299440)" side2="(-9.142550, 4.135110, -1.224240)" normal="(0, 1, 0)" color="#FF00FF" refraction="1.1"/>
<triangle center="(-9.142550, 4.135110, -1.224240)" side1="(-6.755280, 2.573820, -7.246660)" side2="(-8.803830, 0.943640, -3.949340)" normal="(0, 1, 0)" color="#FF00FF" refraction="1.1"/>
<triangle center="(2.235010, 0.174690, 0.961350)" side1="(2.427180, 0.517780, 1.423150)" side2="(-8.433790, 3.361580, 3.431720)" normal="(0, 1, 0)" color="#FF00FF" refraction="1.1"/>
<triangle center="(2.427180, 0.517780, 1.423150)" side1="(-6.456260, 5.965210, 5.506040)" side2="(-8.433790, 3.361580, 3.431720)" normal="(0, 1, 0)" color="#FF00FF" refraction="1.1"/>
<triangle center="(-8.976190, 4.272760, 2.980490)" side1="(-6.701510, 6.377210, 5.302010)" side2="(-7.031260, 7.904390, 3.849340)" normal="(0, 1, 0)" color="#FF00FF" refraction="1.1"/>
<triangle center="(-7.031260, 7.904390, 3.849340)" side1="(-9.142550, 4.135110, -1.224240)" side2="(-8.976190, 4.272760, 2.980490)" normal="(0, 1, 0)" color="#FF00FF" refraction="1.1"/>
<triangle center="(-7.031260, 7.904390, 3.849340)" side1="(-6.142090, 9.825790, 2.296370)" side2="(-8.413100, 6.652490, -1.381730)" normal="(0, 1, 0)" color="#FF00FF" refraction="1.1"/>
<triangle center="(-9.142550, 4.135110, -1.224240)" side1="(-8.413100, 6.652490, -1.381730)" side2="(-7.083970, 5.003970, -6.308350)" normal="(0, 1, 0)" color="#FF00FF" refraction="1.1"/>
<triangle center="(-6.755280, 2.573820, -7.246660)" side1="(-7.083970, 5.003970, -6.308350)" side2="(-2.933290, 5.845920, -9.597530)" normal="(0, 1, 0)" color="#FF00FF" refraction="1.1"/>
<triangle center="(-1.267880, 4.135110, -10.690070)" side1="(-2.933290, 5.845920, -9.597530)" side2="(1.607530, 8.685130, -9.322520)" normal="(0, 1, 0)" color="#FF00FF" refraction="1.1"/>
<triangle center="(4.105210, 7.904390, -9.537370)" side1="(1.607530, 8.685130, -9.322520)" side2="(3.878530, 11.858430, -5.644420)" normal="(0, 1, 0)" color="#FF00FF" refraction="1.1"/>
<triangle center="(6.216500, 11.673670, -4.463780)" side1="(3.878530, 11.858430, -5.644420)" side2="(2.549400, 13.506940, -0.717800)" normal="(0, 1, 0)" color="#FF00FF" refraction="1.1"/>
<triangle center="(3.829230, 13.234960, 1.558640)" side1="(2.549400, 13.506940, -0.717800)" side2="(-1.601280, 12.664990, 2.571380)" normal="(0, 1, 0)" color="#FF00FF" refraction="1.1"/>
<triangle center="(-1.658180, 11.673670, 5.002050)" side1="(-1.601280, 12.664990, 2.571380)" side2="(-6.142090, 9.825790, 2.296370)" normal="(0, 1, 0)" color="#FF00FF" refraction="1.1"/>
